calvos/Engine Release Notes.md
calvos/__init__.py
calvos/__main__.py
calvos/__version__.py
calvos/calvos_components.xsd
calvos/comgen/CAN.py
calvos/comgen/CAN.xml
calvos/comgen/__init__.py
calvos/comgen/doc/comgen_CAN - Integration Manual.md
calvos/comgen/doc/comgen_CAN - Integration Manual.pdf
calvos/comgen/gen/CAN/cog_CAN.py
calvos/comgen/gen/CAN/cog_comgen_CAN_NWID_NODEID_callbacks.c
calvos/comgen/gen/CAN/cog_comgen_CAN_NWID_NODEID_callbacks.h
calvos/comgen/gen/CAN/cog_comgen_CAN_NWID_NODEID_core.c
calvos/comgen/gen/CAN/cog_comgen_CAN_NWID_NODEID_core.h
calvos/comgen/gen/CAN/cog_comgen_CAN_NWID_NODEID_hal.c
calvos/comgen/gen/CAN/cog_comgen_CAN_NWID_NODEID_hal.h
calvos/comgen/gen/CAN/cog_comgen_CAN_NWID_NODEID_node_network.h
calvos/comgen/gen/CAN/cog_comgen_CAN_NWID_includes.h
calvos/comgen/gen/CAN/cog_comgen_CAN_NWID_network.h
calvos/comgen/gen/CAN/cog_comgen_CAN_common.c
calvos/comgen/gen/CAN/cog_comgen_CAN_common.h
calvos/comgen/usr_in/template - CAN Network Definition.ods
calvos/common/__init__.py
calvos/common/codegen.py
calvos/common/codegen.xml
calvos/common/general.py
calvos/common/logsys.py
calvos/common/project.py
calvos/common/project.xml
calvos/common/project_definitions.xml
calvos/common/gen/codegen/cog_USER_general_defs.h
calvos/common/gen/codegen/cog_calvos_types.h
calvos/common/gen/codegen/cog_codegen.py
calvos/common/gen/codegen/cog_static_calvos.h
calvos/common/schemas/_calvos_project.xsd
calvos/common/schemas/_component_defs.xsd
calvos/common/schemas/_general_defs.xsd
calvos/common/schemas/codegen.xsd
calvos/common/usr_in/calvos_project.xml
calvos/common/usr_in/default_data_common-codegen.ods
calvos/demo/calvos_project.xml
calvos/demo/doc/comgen_CAN - Integration Manual.pdf
calvos/demo/out/USER_comgen_CAN_DCM_DR_callbacks.c
calvos/demo/out/USER_comgen_CAN_DCM_DR_callbacks.h
calvos/demo/out/USER_comgen_CAN_DCM_DR_hal.c
calvos/demo/out/USER_comgen_CAN_DCM_DR_hal.h
calvos/demo/out/USER_comgen_CAN_DCM_PS_callbacks.c
calvos-0.0.5.dist-info/LICENSE
calvos-0.0.5.dist-info/METADATA
calvos-0.0.5.dist-info/WHEEL
calvos-0.0.5.dist-info/top_level.txt
calvos-0.0.5.dist-info/RECORD
