Metadata-Version: 2.1
Name: calvos
Version: 0.0.5
Summary: SW utilities for embedded systems
Home-page: https://github.com/calcore-io/calvos
Author: Carlos Francisco Calvillo Cortes
Author-email: carlos.f.calvillo@gmail.com
License: GPLv3
Platform: UNKNOWN
Classifier: License :: OSI Approved :: GNU General Public License v3 (GPLv3)
Classifier: Programming Language :: Python
Classifier: Programming Language :: Python :: 3
Classifier: Programming Language :: Python :: 3.7
Classifier: Programming Language :: Python :: Implementation :: CPython
Classifier: Programming Language :: Python :: Implementation :: PyPy
Requires-Python: >=3.7.0
Requires-Dist: cogapp
Requires-Dist: lxml
Requires-Dist: pyexcel-ods
Requires-Dist: pyexcel
